axor/__init__.py
axor/authentication.py
axor/connection.py
axor/cusips_to_figis.py
axor/fit_johnson_su.py
axor/fit_normal_distribution.py
axor_api-0.1.0.dist-info/METADATA
axor_api-0.1.0.dist-info/WHEEL
axor_api-0.1.0.dist-info/top_level.txt
axor_api-0.1.0.dist-info/RECORD
