Metadata-Version: 2.4
Name: axor-api
Version: 0.1.0
Summary: Python client library for the Deep MM AXOR API - Real-time and historical corporate bond pricing
Author-email: Deep Market Making <support@deepmm.com>
License: MIT
Project-URL: Homepage, https://www.deepmarketmaking.com
Project-URL: Documentation, https://github.com/deepmarketmaking/api#readme
Project-URL: Repository, https://github.com/deepmarketmaking/api
Project-URL: Bug Tracker, https://github.com/deepmarketmaking/api/issues
Keywords: finance,bonds,corporate-bonds,pricing,api,axor,deepmm,deep-mm,deep-market-making
Classifier: Development Status :: 3 - Alpha
Classifier: Intended Audience :: Financial and Insurance Industry
Classifier: Intended Audience :: Developers
Classifier: License :: OSI Approved :: MIT License
Classifier: Programming Language :: Python :: 3
Classifier: Programming Language :: Python :: 3.8
Classifier: Programming Language :: Python :: 3.9
Classifier: Programming Language :: Python :: 3.10
Classifier: Programming Language :: Python :: 3.11
Classifier: Programming Language :: Python :: 3.12
Classifier: Topic :: Office/Business :: Financial
Classifier: Topic :: Scientific/Engineering
Requires-Python: >=3.8
Requires-Dist: boto3>=1.26.0
Requires-Dist: httpx>=0.24.0
Requires-Dist: numpy>=1.24.0
Requires-Dist: pyarrow>=12.0.0
Requires-Dist: scipy>=1.10.0
Requires-Dist: tenacity>=8.2.0
Requires-Dist: websockets>=11.0
Provides-Extra: visualization
Requires-Dist: matplotlib>=3.7.0; extra == "visualization"
Provides-Extra: dev
Requires-Dist: pytest>=7.0; extra == "dev"
Requires-Dist: pytest-asyncio>=0.21.0; extra == "dev"
Requires-Dist: black>=23.0; extra == "dev"
Requires-Dist: flake8>=6.0; extra == "dev"
Requires-Dist: mypy>=1.0; extra == "dev"
